gen_joint_mtide/__init__.py
gen_joint_mtide/core/__init__.py
gen_joint_mtide/core/emg_arbitrary_variance.py
gen_joint_mtide/core/evaluate_gen_models.py
gen_joint_mtide/core/fit_tcopula.R
gen_joint_mtide/core/gen_model_strategies.py
gen_joint_mtide/core/gen_t_copula.R
gen_joint_mtide/core/simulate.py
gen_joint_mtide/data/example_data.csv
gen_joint_mtide-0.1.0.dist-info/METADATA
gen_joint_mtide-0.1.0.dist-info/WHEEL
gen_joint_mtide-0.1.0.dist-info/RECORD
