Metadata-Version: 2.1
Name: gen-joint-mtide
Version: 0.1.0
Summary: Utilities to generate realistic movement time distributions for various user strategies
License: MIT
Author: jgori
Author-email: juliengori@gmail.com
Requires-Python: >=3.10,<4.0
Classifier: License :: OSI Approved :: MIT License
Classifier: Programming Language :: Python :: 3
Classifier: Programming Language :: Python :: 3.10
Classifier: Programming Language :: Python :: 3.11
Classifier: Programming Language :: Python :: 3.12
Requires-Dist: matplotlib (>=3.9.2,<4.0.0)
Requires-Dist: numpy (>=2.1.1,<3.0.0)
Requires-Dist: polars (>=1.7.1,<2.0.0)
Requires-Dist: rpy2 (>=3.5.16,<4.0.0)
Requires-Dist: scipy (>=1.14.1,<2.0.0)
Requires-Dist: seaborn (>=0.13.2,<0.14.0)
